<?xml version="1.0" encoding="ISO-8859-1"?>
<lang>
	<alllabel>tutti</alllabel>
	<allgenre>tutti</allgenre>
	<allselected>del cinema e serie</allselected>
	<anglelabel>aspetto</anglelabel>
	<anylabel>contiene</anylabel>
	<ascending>ascendente</ascending>
	<audiolabel>audio</audiolabel>
	
	<bluelabel>blu</bluelabel>
	
	<certificationlabel>certificazione</certificationlabel>
	<closeremotelabel>close remoto</closeremotelabel>
	<configselected>configurazione</configselected>
	
	<descending>discendente</descending>
	<downlabel>basso</downlabel>
	
	<ejectlabel>espellere</ejectlabel>
	<enterlabel>inserire</enterlabel>
	<episodelabel>episodio</episodelabel>
	
	<fanartshow>fanart</fanartshow>
	<filelabel>file</filelabel>
	<filemodelabel>modalita file</filemodelabel>
	<filmographylabel>filmografia</filmographylabel>
	<formatlabel>formato</formatlabel>
	<fpslabel>fps</fpslabel>
	<fwdlabel>avanti</fwdlabel>
	
	<genrelabel>tipo</genrelabel>
	<genrelistselect>lista dei generi</genrelistselect>
	<genreselected>tipo</genreselected>
	<greenlabel>verde</greenlabel>
	
	<homelabel>casa</homelabel>
	
	<infolabel>info</infolabel>
	
	<language>lingua</language>
	<leftlabel>sinistra</leftlabel>
	
	<menulabel>menu</menulabel>
	<movielabel>del cinema</movielabel>
	<mutelabel>muto</mutelabel>
	<movieselected>del cinema</movieselected>
	
	<namelabel>cognome</namelabel>	
	<nbrow>nb di fila</nbrow>
	<nextremotelabel>prossimo</nextremotelabel>
	<nobiography>biografia assente</nobiography>
	<nobirthday>data di nascita sconosciuta</nobirthday>
	<noplot>non sinossi disponibili</noplot>
	<noposter>non manisfesta</noposter>
	
	<pagelabel>pagina</pagelabel>
	<pauselabel>pausa</pauselabel>
	<personlabel>persona</personlabel>
	<personselected>persona</personselected>
	<personshow>persona</personshow>
	<playerselected>giocatore</playerselected>
	<playlabel>giocare su </playlabel>
	<plotlabel>sinossi</plotlabel>
	<powerlabel>potenza</powerlabel>
	<prevremotelabel>precedente</prevremotelabel>
	
	<ratinglabel>valutazione</ratinglabel>
	<ratingindex>valutazione</ratingindex>
	<redlabel>rosso</redlabel>
	<remotelabel>telecommando</remotelabel>
	<repeatlabel>ripetizione</repeatlabel>
	<resultstext>provocare</resultstext>
	<returnlabel>ritorno</returnlabel>
	<runtimelabel>termine</runtimelabel>
	<rewindlabel>riavvolgere</rewindlabel>
	<rightlabel>diritto</rightlabel>
	
	<searchselected>ricerca</searchselected>
	<seasonlabel>stagione</seasonlabel>
	<seasonselected>stagione</seasonselected>
	<selection>selezione</selection>
	<selectionlabel>selezione</selectionlabel>
	<serieslabel>serie</serieslabel>
	<serieselected>serie</serieselected>
	<setuplabel>impostazione</setuplabel>
	<show>nastro</show>
	<sourcelabel>origine</sourcelabel>
	<startlabel>inizia con</startlabel>
	<stoplabel>stop</stoplabel>
	<studioselected>studio</studioselected>
	<stylelabel>stile</stylelabel>
	<subtitlelabel>sottotitlo</subtitlelabel>
	
	<titlelabel>titolo</titlelabel>
	<timeseeklabel>tempo di ricer.</timeseeklabel>
	<tvmodelabel>modalia tv</tvmodelabel>
	
	<unwatchedselect>non visto</unwatchedselect>
	<uplabel>top</uplabel>
	
	<videolabel>video</videolabel>
	<volumedownlabel>vol-</volumedownlabel>
	<volumeuplabel>vol+</volumeuplabel>
	
	<watchedselect>visto</watchedselect>
	
	<yearlabel>anno</yearlabel>
	<yellowlabel>giallo</yellowlabel>
	
	<zoomlabel>zoom</zoomlabel>
</lang>
